README.md
setup.py
mconv/__init__.py
mconv/cli.py
mconv/conv.py
py_mconv.egg-info/PKG-INFO
py_mconv.egg-info/SOURCES.txt
py_mconv.egg-info/dependency_links.txt
py_mconv.egg-info/entry_points.txt
py_mconv.egg-info/requires.txt
py_mconv.egg-info/top_level.txt